Metadata-Version: 2.4
Name: netzoopy-sponge
Version: 2.0.6
Summary: A package to generate prior gene regulatory networks.
Author-email: Ladislav Hovan <ladislav.hovan@ncmbm.uio.no>
License-Expression: GPL-3.0-or-later
Project-URL: Repository, https://github.com/kuijjerlab/sponge
Keywords: transcription-factors,gene-regulatory-network
Classifier: Development Status :: 5 - Production/Stable
Classifier: Programming Language :: Python :: 3
Classifier: Topic :: Scientific/Engineering :: Bio-Informatics
License-File: LICENSE
Requires-Dist: bioframe
Requires-Dist: numpy
Requires-Dist: pandas
Requires-Dist: pybbi
Requires-Dist: pyjaspar
Requires-Dist: scikit-learn
Requires-Dist: tqdm
Dynamic: license-file
